patch_indices/__init__.py
patch_indices/patch_indices.py
patchgenerator-0.0.2.dist-info/LICENSE.txt
patchgenerator-0.0.2.dist-info/METADATA
patchgenerator-0.0.2.dist-info/WHEEL
patchgenerator-0.0.2.dist-info/top_level.txt
patchgenerator-0.0.2.dist-info/RECORD
