Metadata-Version: 2.1
Name: patchgenerator
Version: 0.0.2
Summary: `Patchgenerator` is a simple tool to generate array indices, with or without overlap, to create numpy array patches. Only requires python.
Home-page: https://github.com/earthobserved/patchgenerator
Author: Earth Observed
Author-email: EarthObserved <info@earthobserved.com>
Project-URL: Homepage, https://github.com/earthobserved/patchgenerator
Project-URL: Bug Tracker, https://github.com/earthobserved/patchgenerator/issues
Classifier: Programming Language :: Python :: 3
Classifier: License :: OSI Approved :: MIT License
Classifier: Operating System :: OS Independent
Requires-Python: >=3.7
License-File: LICENSE.txt
